translate/__init__.py
translate/__version__.py
translate/py.typed
translate/convert/__init__.py
translate/convert/accesskey.py
translate/convert/android2po.py
translate/convert/convert.py
translate/convert/csv2po.py
translate/convert/csv2tbx.py
translate/convert/dtd2po.py
translate/convert/factory.py
translate/convert/flatxml2po.py
translate/convert/html2po.py
translate/convert/ical2po.py
translate/convert/idml2po.py
translate/convert/ini2po.py
translate/convert/json2po.py
translate/convert/md2po.py
translate/convert/moz2po.py
translate/convert/mozfunny2prop.py
translate/convert/mozlang2po.py
translate/convert/odf2xliff.py
translate/convert/oo2po.py
translate/convert/oo2xliff.py
translate/convert/php2po.py
translate/convert/po2csv.py
translate/convert/po2dtd.py
translate/convert/po2flatxml.py
translate/convert/po2html.py
translate/convert/po2ical.py
translate/convert/po2idml.py
translate/convert/po2ini.py
translate/convert/po2json.py
translate/convert/po2md.py
translate/convert/po2moz.py
translate/convert/po2mozlang.py
translate/convert/po2odf.py
translate/convert/po2oo.py
translate/convert/po2php.py
translate/convert/po2prop.py
translate/convert/po2rc.py
translate/convert/po2resx.py
translate/convert/po2sub.py
translate/convert/po2symb.py
translate/convert/po2tiki.py
translate/convert/po2tmx.py
translate/convert/po2toml.py
translate/convert/po2ts.py
translate/convert/po2txt.py
translate/convert/po2web2py.py
translate/convert/po2wordfast.py
translate/convert/po2xliff.py
translate/convert/po2yaml.py
translate/convert/pot2po.py
translate/convert/prop2mozfunny.py
translate/convert/prop2po.py
translate/convert/rc2po.py
translate/convert/resx2po.py
translate/convert/sub2po.py
translate/convert/symb2po.py
translate/convert/tbx2po.py
translate/convert/tiki2po.py
translate/convert/toml2po.py
translate/convert/ts2po.py
translate/convert/txt2po.py
translate/convert/web2py2po.py
translate/convert/xliff2odf.py
translate/convert/xliff2oo.py
translate/convert/xliff2po.py
translate_toolkit-3.18.0.dist-info/licenses/COPYING
translate_toolkit-3.18.0.dist-info/METADATA
translate_toolkit-3.18.0.dist-info/WHEEL
translate_toolkit-3.18.0.dist-info/entry_points.txt
translate_toolkit-3.18.0.dist-info/top_level.txt
translate_toolkit-3.18.0.dist-info/RECORD
