Metadata-Version: 2.4
Name: translate-toolkit
Version: 3.18.0
Summary: Tools and API for translation and localization engineering.
Author-email: Translate <translate-devel@lists.sourceforge.net>
License-Expression: GPL-2.0-or-later
Project-URL: Documentation, https://docs.translatehouse.org/projects/translate-toolkit/
Project-URL: Download, https://github.com/translate/translate/releases/
Project-URL: Homepage, https://toolkit.translatehouse.org/
Project-URL: Issue Tracker, https://github.com/translate/translate/issues
Project-URL: Source Code, https://github.com/translate/translate
Keywords: i18n l10n gettext translate
Platform: any
Classifier: Development Status :: 5 - Production/Stable
Classifier: Environment :: Console
Classifier: Intended Audience :: Developers
Classifier: Operating System :: MacOS :: MacOS X
Classifier: Operating System :: Microsoft :: Windows
Classifier: Operating System :: OS Independent
Classifier: Operating System :: Unix
Classifier: Programming Language :: Python :: 3 :: Only
Classifier: Programming Language :: Python :: 3
Classifier: Programming Language :: Python :: 3.11
Classifier: Programming Language :: Python :: 3.12
Classifier: Programming Language :: Python :: 3.13
Classifier: Programming Language :: Python :: 3.14
Classifier: Programming Language :: Python
Classifier: Topic :: Software Development :: Internationalization
Classifier: Topic :: Software Development :: Libraries :: Python Modules
Classifier: Topic :: Software Development :: Localization
Requires-Python: >=3.11
License-File: COPYING
Requires-Dist: lxml<6.1,>=5.2.0
Requires-Dist: unicode-segmentation-rs<0.3,>=0.2.0
Provides-Extra: all
Requires-Dist: translate-toolkit[chardet,fluent,ical,ini,levenshtein,markdown,php,rc,spellcheck,subtitles,tmserver,toml,trados,yaml]; extra == "all"
Provides-Extra: chardet
Requires-Dist: charset-normalizer<4.0,>=3.4.0; extra == "chardet"
Provides-Extra: fluent
Requires-Dist: fluent.syntax<0.20,>=0.19.0; extra == "fluent"
Provides-Extra: ical
Requires-Dist: vobject==0.9.9; extra == "ical"
Provides-Extra: ini
Requires-Dist: iniparse==0.5; extra == "ini"
Provides-Extra: levenshtein
Requires-Dist: python-Levenshtein>=0.21.0; extra == "levenshtein"
Provides-Extra: markdown
Requires-Dist: mistletoe<1.6.0,>=1.4.0; extra == "markdown"
Provides-Extra: php
Requires-Dist: phply<1.3,>=1.2.6; extra == "php"
Provides-Extra: rc
Requires-Dist: pyparsing<3.4,>=3.2.0; extra == "rc"
Provides-Extra: spellcheck
Requires-Dist: pyenchant==3.3.0; extra == "spellcheck"
Provides-Extra: subtitles
Requires-Dist: aeidon<1.16,>=1.14.1; extra == "subtitles"
Provides-Extra: tmserver
Requires-Dist: cheroot==11.1.2; extra == "tmserver"
Provides-Extra: toml
Requires-Dist: tomlkit<0.14.0,>=0.13.0; extra == "toml"
Provides-Extra: trados
Requires-Dist: BeautifulSoup4>=4.13.0; extra == "trados"
Provides-Extra: yaml
Requires-Dist: ruamel.yaml<0.20.0,>=0.18.0; extra == "yaml"
Dynamic: license-file
